tfw/__init__.py
tfw/my_tf.py
tfw_tf-0.2.dist-info/METADATA
tfw_tf-0.2.dist-info/WHEEL
tfw_tf-0.2.dist-info/top_level.txt
tfw_tf-0.2.dist-info/RECORD
